fabric_fixes/__init__.py
fabric_fixes/monkeyPatch.py
fabric_fixes/version.py
fabric_fixes-0.0.1.dist-info/DESCRIPTION.rst
fabric_fixes-0.0.1.dist-info/METADATA
fabric_fixes-0.0.1.dist-info/RECORD
fabric_fixes-0.0.1.dist-info/WHEEL
fabric_fixes-0.0.1.dist-info/metadata.json
fabric_fixes-0.0.1.dist-info/top_level.txt
