Metadata-Version: 2.0
Name: fabric-fixes
Version: 0.0.1
Summary: Fixes for various deficiencies of fabric
Home-page: http://github.com/adamkerz/fabric-fixes
Author: Adam Kerz
Author-email: github@kerz.id.au
License: BSD 3-Clause
Keywords: fabric
Platform: UNKNOWN
Classifier: Development Status :: 4 - Beta
Classifier: Intended Audience :: Developers
Classifier: Natural Language :: English
Classifier: License :: OSI Approved :: BSD License
Classifier: Operating System :: OS Independent
Classifier: Programming Language :: Python
Classifier: Programming Language :: Python :: 2
Classifier: Programming Language :: Python :: 2.7
Classifier: Programming Language :: Python :: 3
Classifier: Programming Language :: Python :: 3.4
Classifier: Topic :: Software Development :: Libraries :: Python Modules
Requires-Dist: fabric
